LICENSE
README.md
setup.py
senstore/__init__.py
senstore/embedder.py
senstore/requirements.txt
senstore/segmenter.py
senstore.egg-info/PKG-INFO
senstore.egg-info/SOURCES.txt
senstore.egg-info/dependency_links.txt
senstore.egg-info/not-zip-safe
senstore.egg-info/requires.txt
senstore.egg-info/top_level.txt