Metadata-Version: 2.4
Name: senstore
Version: 0.6.2
Summary: Minimalistic vectorized sentence store
Home-page: https://github.com/ptarau/senstore.git
Author: Paul Tarau
Author-email: ptarau@gmail.com
License: MIT
License-File: LICENSE
Requires-Dist: networkx
Requires-Dist: scipy
Requires-Dist: pysbd
Requires-Dist: fastembed
Requires-Dist: vecstore
Dynamic: author
Dynamic: author-email
Dynamic: description
Dynamic: description-content-type
Dynamic: home-page
Dynamic: license
Dynamic: license-file
Dynamic: requires-dist
Dynamic: summary
